.git-pre-commit
.gitignore
CREDITS
HISTORY.rst
LICENSE
MANIFEST.in
Makefile
README.rst
TODO
confix.py
pyproject.toml
setup.py
tox.ini
confix.egg-info/PKG-INFO
confix.egg-info/SOURCES.txt
confix.egg-info/dependency_links.txt
confix.egg-info/top_level.txt
docs/Makefile
docs/README
docs/conf.py
docs/index.rst
docs/make.bat
docs/_static/copybutton.js
docs/_static/favicon.ico
docs/_static/logo.png
docs/_static/sidebar.js
docs/_template/globaltoc.html
docs/_template/indexcontent.html
docs/_template/indexsidebar.html
docs/_template/page.html
docs/_themes/pydoctheme/theme.conf
docs/_themes/pydoctheme/static/pydoctheme.css