Metadata-Version: 2.1
Name: confix
Version: 0.2.2
Summary: Language agnostic configuration parser
Home-page: https://pypi.python.org/pypi/confix
Author: Giampaolo Rodola'
Author-email: g.rodola@gmail.com
License: MIT
Keywords: config,yaml,toml,json,ini,sensitive,password
Platform: Platform Independent
Classifier: Development Status :: 4 - Beta
Classifier: Intended Audience :: Developers
Classifier: Intended Audience :: System Administrators
Classifier: License :: OSI Approved :: MIT License
Classifier: Operating System :: OS Independent
Classifier: Programming Language :: Python :: 2
Classifier: Programming Language :: Python :: 3
Classifier: Programming Language :: Python
Classifier: Topic :: Security
Classifier: Topic :: Software Development :: Libraries :: Python Modules
Classifier: Topic :: Software Development :: Libraries
Classifier: Topic :: System :: Systems Administration
Classifier: Topic :: Utilities
License-File: LICENSE
